PhoenixGeoPy/__init__.py
PhoenixGeoPy/Reader/DataScaling.py
PhoenixGeoPy/Reader/TimeSeries.py
PhoenixGeoPy/Reader/__init__.py
PhoenixGeoPy-1.0.2.dist-info/METADATA
PhoenixGeoPy-1.0.2.dist-info/WHEEL
PhoenixGeoPy-1.0.2.dist-info/top_level.txt
PhoenixGeoPy-1.0.2.dist-info/RECORD
