Metadata-Version: 2.1
Name: PhoenixGeoPy
Version: 1.0.2
Summary: This package enables users to parse and handle Phoenix Geophysics binary time series from the MTU-5C family of receivers.
Author: Phoenix Geophysics Ltd.
Author-email: pypi@phoenix-geophysics.com
License: MIT
Project-URL: Homepage, https://github.com/torresolmx/PhoenixGeoPy
Project-URL: Bug Tracker, https://github.com/torresolmx/PhoenixGeoPy/issues
Classifier: Programming Language :: Python :: 3
Classifier: License :: OSI Approved :: MIT License
Classifier: Operating System :: OS Independent
Requires-Python: >=3.7
Requires-Dist: numpy>=1.20.0
Requires-Dist: matplotlib>=3.4.0
